{"qas": [{"question": "Who did the Mongols give control of Korea?", "id": "5728855d3acd2414000dfa8d", "answers": [{"text": "Uighurs", "answer_start": 28}, {"text": "Uighurs of the Kingdom of Qocho", "answer_start": 28}], "is_impossible": false}, {"question": "Who was the Uighur King of Qocho ranked above?", "id": "5728855d3acd2414000dfa8e", "answers": [{"text": "the Karluk Kara-Khanid ruler", "answer_start": 237}, {"text": "Karluk Kara-Khanid", "answer_start": 241}, {"text": "the Karluk Kara-Khanid ruler", "answer_start": 237}], "is_impossible": false}, {"question": "Who was the Karluk Kara-Khanid ruler ranked above?", "id": "5728855d3acd2414000dfa8f", "answers": [{"text": "the Korean King", "answer_start": 302}, {"text": "Korean King", "answer_start": 306}, {"text": "the Korean King", "answer_start": 302}], "is_impossible": false}, {"question": "Why were the Uighurs ranked higher by the Mongols?", "id": "5728855d3acd2414000dfa90", "answers": [{"text": "the Uighurs surrendered peacefully without violently resisting", "answer_start": 480}, {"text": "Uighurs surrendered peacefully without violently resisting", "answer_start": 484}, {"text": "surrendered peacefully without violently resisting", "answer_start": 492}], "is_impossible": false}, {"plausible_answers": [{"text": "Uighurs", "answer_start": 28}], "question": "Who did the Mongols refuse control of Korea?", "id": "5ad40d50604f3c001a4000c9", "answers": [], "is_impossible": true}, {"plausible_answers": [{"text": "Karluk Kara-Khanid ruler", "answer_start": 241}], "question": " Who was the Uighur King of Qocho ranked below?", "id": "5ad40d50604f3c001a4000ca", "answers": [], "is_impossible": true}, {"plausible_answers": [{"text": "Korean King", "answer_start": 164}], "question": " Who was the Karluk Kara-Khanid ruler ranked below?", "id": "5ad40d50604f3c001a4000cb", "answers": [], "is_impossible": true}, {"plausible_answers": [{"text": "Uighurs surrendered to the Mongols first", "answer_start": 352}], "question": " Why were the Uighurs ranked lower by the Mongols?", "id": "5ad40d50604f3c001a4000cc", "answers": [], "is_impossible": true}], "context": "When the Mongols placed the Uighurs of the Kingdom of Qocho over the Koreans at the court the Korean King objected, then the Mongol Emperor Kublai Khan rebuked the Korean King, saying that the Uighur King of Qocho was ranked higher than the Karluk Kara-Khanid ruler, who in turn was ranked higher than the Korean King, who was ranked last, because the Uighurs surrendered to the Mongols first, the Karluks surrendered after the Uighurs, and the Koreans surrendered last, and that the Uighurs surrendered peacefully without violently resisting."}