{"qas": [{"question": "Who took up the path of violence?", "id": "5730126ba23a5019007fcd09", "answers": [{"text": "Egyptian Islamic Jihad organization", "answer_start": 68}, {"text": "the Egyptian Islamic Jihad organization", "answer_start": 64}, {"text": "Egyptian Islamic Jihad", "answer_start": 68}], "is_impossible": false}, {"question": "When did the Egyptian Islamic Jihad assassinate Anwar Sadat?", "id": "5730126ba23a5019007fcd0a", "answers": [{"text": "1981", "answer_start": 156}, {"text": "1981", "answer_start": 156}, {"text": "1981", "answer_start": 156}], "is_impossible": false}, {"question": "Which leaders did the Islamic extremists attack?", "id": "5730126ba23a5019007fcd0b", "answers": [{"text": "apostate", "answer_start": 273}, {"text": "\"apostate\" leaders of Muslim states,", "answer_start": 272}, {"text": "apostate", "answer_start": 273}], "is_impossible": false}, {"question": "What sin were the leaders the extremists attacked guilty of?", "id": "5730126ba23a5019007fcd0c", "answers": [{"text": "promoted Western/foreign ideas and practices into Islamic societies", "answer_start": 368}, {"text": "held secular leanings or who had introduced or promoted Western/foreign ideas and practices into Islamic societies", "answer_start": 321}, {"text": "secular leanings", "answer_start": 326}], "is_impossible": false}, {"question": "Who wrote a pamphlet outlining the radical ideas of the extremists?", "id": "5730126ba23a5019007fcd0d", "answers": [{"text": "Muhammad Abd al-Salaam Farag", "answer_start": 486}, {"text": "Muhammad Abd al-Salaam Farag", "answer_start": 486}, {"text": "Muhammad Abd al-Salaam Farag", "answer_start": 486}], "is_impossible": false}, {"plausible_answers": [{"text": "Egyptian Islamic Jihad organization", "answer_start": 68}], "question": "Who rejected the path of violence?", "id": "5acfec5577cf76001a6864fc", "answers": [], "is_impossible": true}, {"plausible_answers": [{"text": "1981", "answer_start": 156}], "question": " When did the Egyptian Islamic Jihad support Anwar Sadat?", "id": "5acfec5577cf76001a6864fd", "answers": [], "is_impossible": true}, {"plausible_answers": [{"text": "apostate", "answer_start": 273}], "question": " Which leaders did the Islamic extremists not attack?", "id": "5acfec5577cf76001a6864fe", "answers": [], "is_impossible": true}, {"plausible_answers": [{"text": "promoted Western/foreign ideas and practices into Islamic societies", "answer_start": 368}], "question": " What sin were the leaders the extremists attacked innocent of?", "id": "5acfec5577cf76001a6864ff", "answers": [], "is_impossible": true}, {"plausible_answers": [{"text": "Muhammad Abd al-Salaam Farag", "answer_start": 486}], "question": "Who wrote a pamphlet outlining the non-radical ideas of the extremists?", "id": "5acfec5577cf76001a686500", "answers": [], "is_impossible": true}], "context": "The path of violence and military struggle was then taken up by the Egyptian Islamic Jihad organization responsible for the assassination of Anwar Sadat in 1981. Unlike earlier anti-colonial movements the extremist group directed its attacks against what it believed were \"apostate\" leaders of Muslim states, leaders who held secular leanings or who had introduced or promoted Western/foreign ideas and practices into Islamic societies. Its views were outlined in a pamphlet written by Muhammad Abd al-Salaam Farag, in which he states:"}